{
  "id": "saga_0_8441137569987",
  "title": "墨西哥军方击毙毒枭引发多州暴力事件",
  "category": "社会民生",
  "status": "active",
  "context_summary": "墨西哥军方在哈利斯科州击毙了该国最大贩毒集团之一“哈利斯科州新生代”的头目奥塞格拉，此举导致该州及邻近多个州爆发了包括道路封锁、建筑和车辆纵火在内的报复性暴力事件。事件凸显了墨西哥政府与强大贩毒集团之间长期且激烈的冲突，以及打击有组织犯罪对社会秩序和公共安全的直接冲击。关键方包括墨西哥军方、哈利斯科州新生代贩毒集团以及受影响各州的政府和居民。",
  "events": [
    {
      "date": "20260223",
      "title": "墨西哥军方击毙毒枭引发多州暴力事件",
      "summary": "墨西哥军方在哈利斯科州击毙最大贩毒集团头目奥塞格拉，引发多州暴力封锁与纵火事件，多地发布红色警报并暂停公共交通。",
      "source_url": "https://tv.cctv.com/2026/02/23/VIDECZVBHn2MImSZ7yIE1ofK260223.shtml#sub1",
      "causal_tag": "Inception",
      "importance": 4
    },
    {
      "date": "20260224",
      "title": "墨西哥总统称墨多地骚乱事态已平息",
      "summary": "墨西哥反毒抓捕行动及后续暴力事件致至少73人死亡，含27名安全人员。总统辛鲍姆称多地骚乱已平息，否认美方参与实地抓捕，承认美方提供情报。",
      "source_url": "https://tv.cctv.com/2026/02/24/VIDEenxFl9DtdGnV1oDd4qzd260224.shtml#sub3",
      "causal_tag": "冲突爆发",
      "importance": 4
    }
  ],
  "last_updated": "20260224"
}