{
  "id": "saga_0_9194195975780",
  "title": "美国首都华盛顿因波托马克河污染进入紧急状态",
  "category": "突发事故",
  "status": "active",
  "context_summary": "美国马里兰州一条污水管道于1月19日发生破裂，导致波托马克河遭受污染。该河流经首都华盛顿市西部，是当地重要的饮用水来源之一。事件发生后，华盛顿市长、民主党人鲍泽宣布当地进入紧急状态，并要求联邦政府提供协助。白宫发言人莱维特指责马里兰州州长、民主党人穆尔忽视陈旧的管道维护，导致泄漏发生。此事件凸显了美国基础设施老化问题，并对首都地区的公共健康和水资源安全构成直接威胁。",
  "events": [
    {
      "date": "20260219",
      "title": "美国首都华盛顿因波托马克河污染进入紧急状态",
      "summary": "美国马里兰州污水管道破裂致波托马克河污染，华盛顿市长鲍泽宣布进入紧急状态并求援联邦政府。",
      "source_url": "https://tv.cctv.com/2026/02/19/VIDESR6em2LbC13TNfSOXBRv260219.shtml#sub3",
      "causal_tag": "Inception",
      "importance": 3
    }
  ],
  "last_updated": "20260219"
}