{
  "id": "saga_1_2596707045314",
  "title": "美国明州移民执法行动调整及政府停摆风险",
  "category": "政治外交",
  "status": "active",
  "context_summary": "美国联邦政府调整明尼苏达州移民执法策略，边境事务主管霍曼表示将采取更有针对性的行动，并计划在地方配合下减少执法人员数量。明尼阿波利斯市长反对称行动具政治动机。同时，联邦政府因两党在移民执法和拨款问题上分歧，导致拨款法案受阻，可能引发部分政府停摆。参议院两党达成临时拨款协议，但需两院通过，目前进展不明。",
  "events": [
    {
      "date": "20260130",
      "title": "美国明州移民执法行动调整及政府停摆风险",
      "summary": "美国边境事务主管霍曼称将针对性移民执法，明尼阿波利斯市长反对；缅因州移民执法停止，两党因移民拨款分歧致政府或部分停摆。",
      "source_url": "https://tv.cctv.com/2026/01/30/VIDEddJnkNyhLlT72KOgxmOM260130.shtml",
      "causal_tag": "Inception",
      "importance": 4
    }
  ],
  "last_updated": "20260130"
}