{
  "id": "saga_4a17195e",
  "title": "长江十年禁渔中期评估情况发布",
  "category": "环境政策",
  "status": "active",
  "context_summary": "国务院新闻办公室举行新闻发布会，农业农村部介绍了长江十年禁渔自2021年实施五年来的中期评估情况。评估显示禁渔秩序稳定，取得积极进展：鱼类物种增加，水生生物完整性提升，长江江豚数量恢复，涉渔违法行为下降，退捕渔民得到安置保障。",
  "events": [
    {
      "date": "20260130",
      "title": "长江十年禁渔中期评估情况发布",
      "summary": "长江十年禁渔中期评估显示，禁渔五年后鱼类种类增加，长江江豚数量恢复至1426头，涉渔违法行为下降。",
      "source_url": "https://tv.cctv.com/2026/01/30/VIDErketpPdehK8b7NgVDXzY260130.shtml",
      "causal_tag": "Statement",
      "importance": 4
    }
  ],
  "last_updated": "20260130"
}